corona_alrimi/__init__.py
corona_alrimi/corona_etc.py
corona_alrimi/overseas.py
corona_alrimi/today_corona.py
corona_alrimi/uptodate_checkup.py
corona_alrimi-0.0.4.dist-info/LICENSE
corona_alrimi-0.0.4.dist-info/METADATA
corona_alrimi-0.0.4.dist-info/WHEEL
corona_alrimi-0.0.4.dist-info/top_level.txt
corona_alrimi-0.0.4.dist-info/RECORD
